pygops/__init__.py
pygops/go_launcher.py
pygops/go_server.py
pygops/go_thread.py
pygops/scripts/debug.bat
pygops/scripts/go_dummy.go
pygops/scripts/go_launcher.ps1
pygops-0.2.dist-info/licenses/LICENSE
pygops-0.2.dist-info/METADATA
pygops-0.2.dist-info/WHEEL
pygops-0.2.dist-info/top_level.txt
pygops-0.2.dist-info/RECORD
