Metadata-Version: 2.4
Name: pygops
Version: 0.2
Summary: Python wrapper for Go applications with PowerShell launcher
Author: PyGoPS Team
License: MIT
Project-URL: Homepage, https://github.com/genderlesspit/pygops
Requires-Python: >=3.8
License-File: LICENSE
Requires-Dist: loguru>=0.5.3
Requires-Dist: toomanyports>=0.1
Requires-Dist: aiohttp>=3.8.1
Dynamic: license-file
